LICENSE
MANIFEST.in
README.rst
requirements.txt
setup.cfg
setup.py
versioneer.py
s3lncoll/__init__.py
s3lncoll/_version.py
s3lncoll/cmd.py
s3lncoll/linestream.py
s3lncoll/main.py
s3lncoll/rotatingfile_ctx.py
s3lncoll.egg-info/PKG-INFO
s3lncoll.egg-info/SOURCES.txt
s3lncoll.egg-info/dependency_links.txt
s3lncoll.egg-info/entry_points.txt
s3lncoll.egg-info/requires.txt
s3lncoll.egg-info/top_level.txt
s3lncoll.egg-info/zip-safe