Metadata-Version: 1.0
Name: s3lncoll
Version: 0.1.post13
Summary: Line stream s3 files into ~uniform lumps in S3
Home-page: https://pypi.python.org/pypi/s3lncoll
Author: J C Lawrence
Author-email: claw@kanga.nu
License: LGPL v3.0
Keywords: S3 aggregate tarball compress
Platform: UNKNOWN
